bw_recipe_2016/__init__.py
bw_recipe_2016/base.py
bw_recipe_2016/biosphere.py
bw_recipe_2016/chemidplus.py
bw_recipe_2016/config.py
bw_recipe_2016/endpoints.py
bw_recipe_2016/excel_extraction.py
bw_recipe_2016/extraction.py
bw_recipe_2016/version.py
bw_recipe_2016/categories/__init__.py
bw_recipe_2016/categories/eutrophication.py
bw_recipe_2016/categories/global_warming.py
bw_recipe_2016/categories/ionizing_radiation.py
bw_recipe_2016/categories/land.py
bw_recipe_2016/categories/ozone_formation.py
bw_recipe_2016/categories/particulate_matter.py
bw_recipe_2016/categories/resources.py
bw_recipe_2016/categories/stratospheric_ozone_depletion.py
bw_recipe_2016/categories/terrestrial_acidification.py
bw_recipe_2016/categories/toxicity.py
bw_recipe_2016/categories/water.py
bw_recipe_2016/data/ReCiPe2016_CFs_v1.0_20161004.xlsx
bw_recipe_2016/data/ReCiPe2016_CFs_v1.1_20170929.xlsx
bw_recipe_2016/data/ReCiPe2016_CFs_v1.1_20180117.xlsx
bw_recipe_2016/data/chemid_cache.json
bw_recipe_2016/data/~$ReCiPe2016_CFs_v1.1_20180117.xlsx
bw_recipe_2016/strategies/__init__.py
bw_recipe_2016/strategies/eutrophication.py
bw_recipe_2016/strategies/formatting.py
bw_recipe_2016/strategies/global_warming.py
bw_recipe_2016/strategies/ionizing_radiation.py
bw_recipe_2016/strategies/land.py
bw_recipe_2016/strategies/matching.py
bw_recipe_2016/strategies/names.py
bw_recipe_2016/strategies/ozone_formation.py
bw_recipe_2016/strategies/particulate_matter.py
bw_recipe_2016/strategies/resources.py
bw_recipe_2016/strategies/string_manipulation.py
bw_recipe_2016/strategies/toxicity.py
bw_recipe_2016/strategies/validation.py
bw_recipe_2016-0.3.dist-info/LICENSE
bw_recipe_2016-0.3.dist-info/METADATA
bw_recipe_2016-0.3.dist-info/WHEEL
bw_recipe_2016-0.3.dist-info/top_level.txt
bw_recipe_2016-0.3.dist-info/RECORD
