Metadata-Version: 2.1
Name: bw-recipe-2016
Version: 0.3
Summary: Import ReCiPe 2016 into Brightway2
Home-page: https://github.com/brightway-lca/bw_recipe_2016
Author: Chris Mutel
Author-email: cmutel@gmail.com
License: BSD 3-clause
Platform: UNKNOWN
Classifier: Intended Audience :: End Users/Desktop
Classifier: Intended Audience :: Developers
Classifier: Intended Audience :: Science/Research
Classifier: License :: OSI Approved :: BSD License
Classifier: Operating System :: MacOS :: MacOS X
Classifier: Operating System :: Microsoft :: Windows
Classifier: Operating System :: POSIX
Classifier: Programming Language :: Python
Classifier: Programming Language :: Python :: 3
Classifier: Programming Language :: Python :: 3.5
Classifier: Programming Language :: Python :: 3.6
Classifier: Programming Language :: Python :: 3.7
Requires-Dist: bw2io
Requires-Dist: bw2data
Requires-Dist: requests
